[{"ID":300001,"name":"特锐德","industry":"制造业","grow":19.9,"hold":27856,"date":"2009年10月30日","capital":"200,400,000.00 ","circulate":"192,840,000.00 ","site":"www.qdtgood.com"},
{"ID":300002,"name":"神州泰岳","industry":"信息技术","grow":150.6,"hold":33623,"date":"2009年10月30日","capital":"613,413,920.00 ","circulate":"315,687,336.00 ","site":"www.ultrapower.com.cn"},
{"ID":300003,"name":"乐普医疗","industry":"制造业","grow":9.3,"hold":-32505,"date":"2009年10月30日","capital":"812,000,000.00 ","circulate":"686,106,725.00 ","site":"www.lepumedical.com"},
{"ID":300004,"name":"南风股份","industry":"制造业","grow":-24.8,"hold":9531,"date":"2009年10月30日","capital":"188,000,000.00 ","circulate":"137,032,416.00 ","site":"www.ntfan.com"},
{"ID":300005,"name":"探路者","industry":"制造业","grow":1.6,"hold":37867,"date":"2009年10月30日","capital":"423,192,674.00 ","circulate":"225,752,975.00 ","site":"www.toread.com.cn"},
{"ID":300006,"name":"莱美药业","industry":"制造业","grow":-20.5,"hold":2903,"date":"2009年10月30日","capital":"183,000,000.00 ","circulate":"107,233,253.00 ","site":"www.cqlummy.com"},
{"ID":300007,"name":"汉威电子","industry":"制造业","grow":12.6,"hold":37501,"date":"2009年10月30日","capital":"118,000,000.00 ","circulate":"67,850,081.00 ","site":"www.hwsensor.com"},
{"ID":300008,"name":"上海佳豪","industry":"科研服务","grow":20.3,"hold":39397,"date":"2009年10月30日","capital":"218,484,000.00 ","circulate":"155,724,269.00 ","site":"www.bestwaysh.com"},
{"ID":300009,"name":"安科生物","industry":"制造业","grow":298.2,"hold":48056,"date":"2009年10月30日","capital":"241,144,981.00 ","circulate":"128,531,710.00 ","site":"www.ankebio.com"},
{"ID":300010,"name":"立思辰","industry":"信息技术","grow":47.4,"hold":-11515,"date":"2009年10月30日","capital":"260,867,333.00 ","circulate":"147,239,055.00 ","site":"www.lanxum.com"},
{"ID":300011,"name":"鼎汉技术","industry":"制造业","grow":45.0,"hold":16669,"date":"2009年10月30日","capital":"231,192,000.00 ","circulate":"179,349,654.00 ","site":"www.dinghantech.com"},
{"ID":300012,"name":"华测检测","industry":"科研服务","grow":78.9,"hold":-16983,"date":"2009年10月30日","capital":"369,387,000.00 ","circulate":"176,194,366.00 ","site":"www.cti-cert.com"},
{"ID":300013,"name":"新宁物流","industry":"运输仓储","grow":200.9,"hold":46879,"date":"2009年10月30日","capital":"90,000,000.00 ","circulate":"49,095,000.00 ","site":"www.xinning.com.cn"},
{"ID":300014,"name":"亿纬锂能","industry":"制造业","grow":-91.2,"hold":35532,"date":"2009年10月30日","capital":"199,001,840.00 ","circulate":"154,004,178.00 ","site":"www.evebattery.com"},
{"ID":300015,"name":"爱尔眼科","industry":"卫生","grow":-54.1,"hold":47796,"date":"2009年10月30日","capital":"432,646,500.00 ","circulate":"340,445,220.00 ","site":"www.aierchina.com"},
{"ID":300016,"name":"北陆药业","industry":"制造业","grow":48.9,"hold":-40932,"date":"2009年10月30日","capital":"305,498,208.00 ","circulate":"243,195,096.00 ","site":"www.beilu.com.cn"},
{"ID":300017,"name":"网宿科技","industry":"信息技术","grow":27.7,"hold":-13693,"date":"2009年10月30日","capital":"155,291,786.00 ","circulate":"100,373,762.00 ","site":"www.chinanetcenter.com"},
{"ID":300018,"name":"中元华电","industry":"制造业","grow":21.0,"hold":-6091,"date":"2009年10月30日","capital":"195,000,000.00 ","circulate":"151,046,250.00 ","site":"www.zyhd.com.cn"},
{"ID":300019,"name":"硅宝科技","industry":"制造业","grow":-67.9,"hold":19193,"date":"2009年10月30日","capital":"163,200,000.00 ","circulate":"118,554,240.00 ","site":"www.cnguibao.com"},
{"ID":300020,"name":"银江股份","industry":"信息技术","grow":233.9,"hold":-9489,"date":"2009年10月30日","capital":"241,427,400.00 ","circulate":"236,288,614.00 ","site":"www.enjoyor.net"},
{"ID":300021,"name":"大禹节水","industry":"制造业","grow":-8.3,"hold":-14990,"date":"2009年10月30日","capital":"278,600,000.00 ","circulate":"162,463,087.00 ","site":"www.gsdyjsgs.com"},
{"ID":300022,"name":"吉峰农机","industry":"批发零售","grow":-70.9,"hold":46589,"date":"2009年10月30日","capital":"357,400,000.00 ","circulate":"315,805,997.00 ","site":"www.gifore.com"},
{"ID":300023,"name":"宝德股份","industry":"制造业","grow":40.8,"hold":-5193,"date":"2009年10月30日","capital":"90,000,000.00 ","circulate":"34,898,438.00 ","site":"www.bode-e.com"},
{"ID":300024,"name":"机器人","industry":"制造业","grow":17.5,"hold":-41583,"date":"2009年10月30日","capital":"297,660,000.00 ","circulate":"287,229,794.00 ","site":"www.siasun.com"},
{"ID":300025,"name":"华星创业","industry":"信息技术","grow":-50.1,"hold":-35675,"date":"2009年10月30日","capital":"156,000,000.00 ","circulate":"92,975,375.00 ","site":"www.hxcy.com.cn"},
{"ID":300026,"name":"红日药业","industry":"制造业","grow":168.5,"hold":9256,"date":"2009年10月30日","capital":"373,972,318.00 ","circulate":"250,918,208.00 ","site":"www.chasesun.cn"},
{"ID":300027,"name":"华谊兄弟","industry":"文化传播","grow":295.5,"hold":-36202,"date":"2009年10月30日","capital":"604,800,000.00 ","circulate":"408,713,700.00 ","site":"www.huayimedia.com"},
{"ID":300028,"name":"金亚科技","industry":"制造业","grow":-52.5,"hold":15805,"date":"2009年10月30日","capital":"264,600,000.00 ","circulate":"192,607,200.00 ","site":"www.geeya.cn"},
{"ID":300029,"name":"天龙光电","industry":"制造业","grow":34.2,"hold":40327,"date":"2009年12月25日","capital":"200,000,000.00 ","circulate":"174,792,406.00 ","site":"www.hstl.cn"},
{"ID":300030,"name":"阳普医疗","industry":"制造业","grow":-41.2,"hold":-37580,"date":"2009年12月25日","capital":"148,000,000.00 ","circulate":"109,062,941.00 ","site":"www.improve-medical.com"},
{"ID":300031,"name":"宝通带业","industry":"制造业","grow":40.7,"hold":48760,"date":"2009年12月25日","capital":"150,000,000.00 ","circulate":"106,678,783.00 ","site":"www.btdy.com"},
{"ID":300032,"name":"金龙机电","industry":"制造业","grow":48.2,"hold":-5052,"date":"2009年12月25日","capital":"285,400,000.00 ","circulate":"257,725,000.00 ","site":"www.kotl.com.cn"},
{"ID":300033,"name":"同花顺","industry":"信息技术","grow":44.9,"hold":27527,"date":"2009年12月25日","capital":"134,400,000.00 ","circulate":"61,466,635.00 ","site":"www.10jqka.com.cn"},
{"ID":300034,"name":"钢研高纳","industry":"制造业","grow":-26.9,"hold":50535,"date":"2009年12月25日","capital":"211,988,154.00 ","circulate":"211,988,154.00 ","site":"www.cisri-gaona.com.cn"},
{"ID":300035,"name":"中科电气","industry":"制造业","grow":-25.4,"hold":-42087,"date":"2009年12月25日","capital":"179,887,500.00 ","circulate":"109,873,250.00 ","site":"www.cseco.cn"},
{"ID":300036,"name":"超图软件","industry":"信息技术","grow":106.3,"hold":38154,"date":"2009年12月25日","capital":"120,000,000.00 ","circulate":"87,228,800.00 ","site":"www.supermap.com.cn"},
{"ID":300037,"name":"新宙邦","industry":"制造业","grow":-57.3,"hold":21709,"date":"2010年1月8日","capital":"171,200,000.00 ","circulate":"91,746,248.00 ","site":"www.capchem.com"},
{"ID":300038,"name":"梅泰诺","industry":"制造业","grow":57.1,"hold":-11642,"date":"2010年1月8日","capital":"157,309,389.00 ","circulate":"96,936,000.00 ","site":"www.meteno.com.cn"},
{"ID":300039,"name":"上海凯宝","industry":"制造业","grow":0.8,"hold":47021,"date":"2010年1月8日","capital":"526,080,000.00 ","circulate":"385,494,000.00 ","site":"www.xykb.com"},
{"ID":300040,"name":"九洲电气","industry":"制造业","grow":67.0,"hold":15356,"date":"2010年1月8日","capital":"277,800,000.00 ","circulate":"198,448,500.00 ","site":"www.jze.com.cn"},
{"ID":300041,"name":"回天胶业","industry":"制造业","grow":265.2,"hold":8493,"date":"2010年1月8日","capital":"168,954,920.00 ","circulate":"124,272,682.00 ","site":"www.huitian.net.cn"},
{"ID":300042,"name":"朗科科技","industry":"制造业","grow":32.9,"hold":36540,"date":"2010年1月8日","capital":"133,600,000.00 ","circulate":"81,180,775.00 ","site":"www.netac.com.cn"},
{"ID":300043,"name":"星辉车模","industry":"制造业","grow":46.9,"hold":26045,"date":"2010年1月20日","capital":"241,781,794.00 ","circulate":"93,820,620.00 ","site":"www.rastar.cn"},
{"ID":300044,"name":"赛为智能","industry":"信息技术","grow":291.1,"hold":18271,"date":"2010年1月20日","capital":"220,000,000.00 ","circulate":"128,746,944.00 ","site":"www.szsunwin.com"},
{"ID":300045,"name":"华力创通","industry":"制造业","grow":32.3,"hold":46041,"date":"2010年1月20日","capital":"268,000,000.00 ","circulate":"140,767,500.00 ","site":"www.hwacreate.com.cn"},
{"ID":300046,"name":"台基股份","industry":"制造业","grow":28.2,"hold":47830,"date":"2010年1月20日","capital":"142,080,000.00 ","circulate":"89,160,000.00 ","site":"www.tech-sem.com"},
{"ID":300047,"name":"天源迪科","industry":"信息技术","grow":40.6,"hold":-18473,"date":"2010年1月20日","capital":"315,544,200.00 ","circulate":"170,625,830.00 ","site":"www.tydic.com"},
{"ID":300048,"name":"合康变频","industry":"制造业","grow":45.6,"hold":-27001,"date":"2010年1月20日","capital":"338,144,800.00 ","circulate":"266,237,800.00 ","site":"www.hiconics.com"},
{"ID":300049,"name":"福瑞股份","industry":"制造业","grow":44.5,"hold":-5136,"date":"2010年1月20日","capital":"125,060,000.00 ","circulate":"108,830,461.00 ","site":"www.fu-rui.com"},
{"ID":300050,"name":"世纪鼎利","industry":"信息技术","grow":-49.6,"hold":-10453,"date":"2010年1月20日","capital":"216,000,000.00 ","circulate":"85,087,750.00 ","site":"www.dinglicom.com"},
{"ID":300051,"name":"三五互联","industry":"信息技术","grow":7.1,"hold":20653,"date":"2010年2月11日","capital":"321,000,000.00 ","circulate":"169,633,150.00 ","site":"www.35.com"},
{"ID":300052,"name":"中青宝","industry":"信息技术","grow":42.9,"hold":29049,"date":"2010年2月11日","capital":"130,000,000.00 ","circulate":"88,486,255.00 ","site":"www.zqgame.com"},
{"ID":300053,"name":"欧比特","industry":"制造业","grow":47.0,"hold":35648,"date":"2010年2月11日","capital":"200,000,000.00 ","circulate":"147,599,750.00 ","site":"www.myorbita.net"},
{"ID":300054,"name":"鼎龙股份","industry":"制造业","grow":7.0,"hold":-3981,"date":"2010年2月11日","capital":"272,400,000.00 ","circulate":"173,863,130.00 ","site":"www.dinglongchem.com"},
{"ID":300055,"name":"万邦达","industry":"建筑业","grow":21.7,"hold":-4544,"date":"2010年2月26日","capital":"228,800,000.00 ","circulate":"168,555,530.00 ","site":"www.waterbd.cn"},
{"ID":300056,"name":"三维丝","industry":"制造业","grow":-21.2,"hold":6088,"date":"2010年2月26日","capital":"93,600,000.00 ","circulate":"58,801,645.00 ","site":"www.savings.com.cn"},
{"ID":300057,"name":"万顺股份","industry":"制造业","grow":20.9,"hold":-5802,"date":"2010年2月26日","capital":"422,000,000.00 ","circulate":"188,450,000.00 ","site":"www.wanshun.cn"},
{"ID":300058,"name":"蓝色光标","industry":"商务服务","grow":-13.7,"hold":-42699,"date":"2010年2月26日","capital":"402,729,641.00 ","circulate":"264,188,021.00 ","site":"www.bluefocusgroup.com"},
{"ID":300059,"name":"东方财富","industry":"信息技术","grow":113.6,"hold":33977,"date":"2010年3月19日","capital":"672,000,000.00 ","circulate":"512,496,432.00 ","site":"www.eastmoney.com"},
{"ID":300061,"name":"康耐特","industry":"制造业","grow":152.0,"hold":40744,"date":"2010年3月19日","capital":"96,000,000.00 ","circulate":"55,683,600.00 ","site":"www.conantoptical.com"},
{"ID":300062,"name":"中能电气","industry":"制造业","grow":11.3,"hold":-19686,"date":"2010年3月19日","capital":"154,510,000.00 ","circulate":"77,631,400.00 ","site":"www.ceepower.com"},
{"ID":300063,"name":"天龙集团","industry":"制造业","grow":-88.7,"hold":-14449,"date":"2010年3月26日","capital":"100,500,000.00 ","circulate":"46,448,800.00 ","site":"www.tlym.cn"},
{"ID":300064,"name":"豫金刚石","industry":"制造业","grow":17.6,"hold":7884,"date":"2010年3月26日","capital":"608,000,000.00 ","circulate":"575,550,016.00 ","site":"www.sinocrystal.com.cn"},
{"ID":300065,"name":"海兰信","industry":"制造业","grow":87.4,"hold":29175,"date":"2010年3月26日","capital":"105,252,970.00 ","circulate":"80,404,961.00 ","site":"www.highlander.com.cn"},
{"ID":300066,"name":"三川股份","industry":"制造业","grow":256.8,"hold":-31716,"date":"2010年3月26日","capital":"155,974,758.00 ","circulate":"106,090,798.00 ","site":"www.ytsanchuan.com"},
{"ID":300067,"name":"安诺其","industry":"制造业","grow":38.2,"hold":28768,"date":"2010年4月21日","capital":"160,500,000.00 ","circulate":"90,498,557.00 ","site":"www.anoky.com.cn"},
{"ID":300068,"name":"南都电源","industry":"制造业","grow":-92.2,"hold":-16399,"date":"2010年4月21日","capital":"599,200,000.00 ","circulate":"354,731,518.00 ","site":"www.naradapower.com"},
{"ID":300069,"name":"金利华电","industry":"制造业","grow":120.9,"hold":-2648,"date":"2010年4月21日","capital":"117,000,000.00 ","circulate":"54,885,599.00 ","site":"www.jlhdq.com"},
{"ID":300070,"name":"碧水源","industry":"公共环保","grow":211.3,"hold":-8545,"date":"2010年4月21日","capital":"885,768,866.00 ","circulate":"512,529,690.00 ","site":"www.originwater.com"},
{"ID":300071,"name":"华谊嘉信","industry":"商务服务","grow":-85.6,"hold":15263,"date":"2010年4月21日","capital":"155,265,816.00 ","circulate":"111,111,103.00 ","site":"www.spearhead.com.cn"},
{"ID":300072,"name":"三聚环保","industry":"制造业","grow":200.3,"hold":21793,"date":"2010年4月27日","capital":"505,804,000.00 ","circulate":"457,123,973.00 ","site":"www.sanju.cn"},
{"ID":300073,"name":"当升科技","industry":"制造业","grow":20.8,"hold":-15764,"date":"2010年4月27日","capital":"160,000,000.00 ","circulate":"152,117,473.00 ","site":"www.easpring.com.cn"},
{"ID":300074,"name":"华平股份","industry":"信息技术","grow":37.8,"hold":-12224,"date":"2010年4月27日","capital":"220,000,000.00 ","circulate":"125,308,506.00 ","site":"www.avcon.com.cn"},
{"ID":300075,"name":"数字政通","industry":"信息技术","grow":37.5,"hold":48714,"date":"2010年4月27日","capital":"126,000,000.00 ","circulate":"74,085,765.00 ","site":"www.egova.com.cn"},
{"ID":300076,"name":"宁波GQY","industry":"制造业","grow":15.4,"hold":68,"date":"2010年4月30日","capital":"106,000,000.00 ","circulate":"81,223,263.00 ","site":"www.gqy.com.cn"},
{"ID":300077,"name":"国民技术","industry":"制造业","grow":-24.4,"hold":49495,"date":"2010年4月30日","capital":"272,000,000.00 ","circulate":"249,050,750.00 ","site":"www.nationz.com.cn"},
{"ID":300078,"name":"中瑞思创","industry":"制造业","grow":-70.9,"hold":-32561,"date":"2010年4月30日","capital":"167,500,000.00 ","circulate":"78,629,688.00 ","site":"www.century-cn.com"},
{"ID":300079,"name":"数码视讯","industry":"制造业","grow":21.7,"hold":28436,"date":"2010年4月30日","capital":"339,352,888.00 ","circulate":"288,298,781.00 ","site":"www.sumavision.com"},
{"ID":300080,"name":"新大新材","industry":"制造业","grow":294.9,"hold":-29018,"date":"2010年6月25日","capital":"502,804,021.00 ","circulate":"210,335,126.00 ","site":"www.xindaxin.cn"},
{"ID":300081,"name":"恒信移动","industry":"批发零售","grow":155.5,"hold":51401,"date":"2010年5月20日","capital":"134,000,000.00 ","circulate":"82,167,756.00 ","site":"www.hxgro.com"},
{"ID":300082,"name":"奥克股份","industry":"制造业","grow":241.4,"hold":-4154,"date":"2010年5月20日","capital":"336,960,000.00 ","circulate":"336,921,000.00 ","site":"www.oxiranchem.com"},
{"ID":300083,"name":"劲胜股份","industry":"制造业","grow":28.8,"hold":-1460,"date":"2010年5月20日","capital":"200,000,000.00 ","circulate":"200,000,000.00 ","site":"www.januscn.com"},
{"ID":300084,"name":"海默科技","industry":"采矿业","grow":15.1,"hold":-3045,"date":"2010年5月20日","capital":"128,000,000.00 ","circulate":"91,254,692.00 ","site":"www.haimo.com.cn"},
{"ID":300085,"name":"银之杰","industry":"信息技术","grow":-7.3,"hold":-13451,"date":"2010年5月26日","capital":"120,000,000.00 ","circulate":"62,119,266.00 ","site":"www.yinzhijie.com"},
{"ID":300086,"name":"康芝药业","industry":"制造业","grow":39.9,"hold":-33546,"date":"2010年5月26日","capital":"200,000,000.00 ","circulate":"70,689,656.00 ","site":"www.honz.com.cn"},
{"ID":300087,"name":"荃银高科","industry":"农林牧渔","grow":-68.4,"hold":4595,"date":"2010年5月26日","capital":"105,600,000.00 ","circulate":"74,614,600.00 ","site":"www.winallseed.com"},
{"ID":300088,"name":"长信科技","industry":"制造业","grow":14.8,"hold":-17616,"date":"2010年5月26日","capital":"489,450,000.00 ","circulate":"380,433,750.00 ","site":"www.token-ito.com"},
{"ID":300089,"name":"长城集团","industry":"制造业","grow":231.5,"hold":32228,"date":"2010年6月25日","capital":"150,000,000.00 ","circulate":"85,022,250.00 ","site":"www.thegreatwall-china.com"},
{"ID":300090,"name":"盛运股份","industry":"制造业","grow":12.4,"hold":37055,"date":"2010年6月25日","capital":"255,272,170.00 ","circulate":"186,126,670.00 ","site":"www.300090.com.cn"},
{"ID":300091,"name":"金通灵","industry":"制造业","grow":37.0,"hold":39486,"date":"2010年6月25日","capital":"209,000,000.00 ","circulate":"122,648,750.00 ","site":"www.jtlfans.com"},
{"ID":300092,"name":"科新机电","industry":"制造业","grow":37.4,"hold":35923,"date":"2010年7月8日","capital":"91,000,000.00 ","circulate":"50,608,511.00 ","site":"www.sckxjd.com"},
{"ID":300093,"name":"金刚玻璃","industry":"制造业","grow":39.3,"hold":30524,"date":"2010年7月8日","capital":"216,000,000.00 ","circulate":"215,263,500.00 ","site":"www.golden-glass.cn"},
{"ID":300094,"name":"国联水产","industry":"农林牧渔","grow":134.6,"hold":1617,"date":"2010年7月8日","capital":"352,000,000.00 ","circulate":"351,224,567.00 ","site":"www.gl-fish.com"},
{"ID":300095,"name":"华伍股份","industry":"制造业","grow":-97.7,"hold":-14022,"date":"2010年7月28日","capital":"100,100,000.00 ","circulate":"35,100,000.00 ","site":"www.hua-wu.com"},
{"ID":300096,"name":"易联众","industry":"信息技术","grow":33.7,"hold":45770,"date":"2010年7月28日","capital":"172,000,000.00 ","circulate":"93,870,000.00 ","site":"www.ylzinfo.com"},
{"ID":300097,"name":"智云股份","industry":"制造业","grow":-23.3,"hold":3802,"date":"2010年7月28日","capital":"60,000,000.00 ","circulate":"27,309,938.00 ","site":"www.zhiyun-cn.com"},
{"ID":300098,"name":"高新兴","industry":"制造业","grow":24.8,"hold":6528,"date":"2010年7月28日","capital":"184,020,000.00 ","circulate":"62,109,840.00 ","site":"www.gosuncn.com"},
{"ID":300099,"name":"尤洛卡","industry":"制造业","grow":-73.7,"hold":37021,"date":"2010年8月6日","capital":"206,700,000.00 ","circulate":"68,882,424.00 ","site":"www.uroica.com.cn"},
{"ID":300100,"name":"双林股份","industry":"制造业","grow":193.2,"hold":11963,"date":"2010年8月6日","capital":"280,500,000.00 ","circulate":"100,500,000.00 ","site":"www.shuanglin.cn"},
{"ID":300101,"name":"国腾电子","industry":"制造业","grow":36.3,"hold":40987,"date":"2010年8月6日","capital":"278,000,000.00 ","circulate":"164,257,348.00 ","site":"www.gotecom.com"},
{"ID":300102,"name":"乾照光电","industry":"制造业","grow":-21.7,"hold":4964,"date":"2010年8月12日","capital":"295,000,000.00 ","circulate":"143,102,875.00 ","site":"www.changelight.com.cn"},
{"ID":300103,"name":"达刚路机","industry":"制造业","grow":-37.1,"hold":7581,"date":"2010年8月12日","capital":"211,734,000.00 ","circulate":"64,392,035.00 ","site":"www.sxdagang.com"},
{"ID":300104,"name":"乐视网","industry":"信息技术","grow":-68.0,"hold":8378,"date":"2010年8月12日","capital":"794,200,000.00 ","circulate":"303,271,384.00 ","site":"www.letv.com"},
{"ID":300105,"name":"龙源技术","industry":"制造业","grow":39.1,"hold":-19672,"date":"2010年8月20日","capital":"285,120,000.00 ","circulate":"71,280,000.00 ","site":"www.lypower.com"},
{"ID":300106,"name":"西部牧业","industry":"农林牧渔","grow":-37.7,"hold":-42753,"date":"2010年8月20日","capital":"117,000,000.00 ","circulate":"59,707,811.00 ","site":"www.xjxbmy.com"},
{"ID":300107,"name":"建新股份","industry":"制造业","grow":127.3,"hold":29144,"date":"2010年8月20日","capital":"133,800,000.00 ","circulate":"39,300,000.00 ","site":"www.jianxinchemical.com"},
{"ID":300108,"name":"双龙股份","industry":"制造业","grow":250.2,"hold":46267,"date":"2010年8月25日","capital":"135,200,000.00 ","circulate":"81,087,646.00 ","site":"www.thslhg.com"},
{"ID":300109,"name":"新开源","industry":"制造业","grow":-48.8,"hold":35374,"date":"2010年8月25日","capital":"115,200,000.00 ","circulate":"68,215,300.00 ","site":"www.china-pvp.com"},
{"ID":300110,"name":"华仁药业","industry":"制造业","grow":49.8,"hold":43265,"date":"2010年8月25日","capital":"436,627,000.00 ","circulate":"199,310,190.00 ","site":"www.qdhuaren.com"},
{"ID":300111,"name":"向日葵","industry":"制造业","grow":13.7,"hold":-23834,"date":"2010年8月27日","capital":"509,000,000.00 ","circulate":"170,004,675.00 ","site":"www.sunowe.com.cn"},
{"ID":300112,"name":"万讯自控","industry":"制造业","grow":42.2,"hold":-8262,"date":"2010年8月27日","capital":"161,167,500.00 ","circulate":"40,500,000.00 ","site":"www.maxonic.com.cn"},
{"ID":300113,"name":"顺网科技","industry":"信息技术","grow":-9.0,"hold":-29696,"date":"2010年8月27日","capital":"132,000,000.00 ","circulate":"59,521,782.00 ","site":"www.shunwang.com"},
{"ID":300114,"name":"中航电测","industry":"制造业","grow":91.5,"hold":-26831,"date":"2010年8月27日","capital":"156,000,000.00 ","circulate":"43,368,000.00 ","site":"www.zemic.com.cn"},
{"ID":300115,"name":"长盈精密","industry":"制造业","grow":16.4,"hold":22146,"date":"2010年9月2日","capital":"258,000,000.00 ","circulate":"110,474,929.00 ","site":"www.ewpt.cn"},
{"ID":300116,"name":"坚瑞消防","industry":"制造业","grow":141.2,"hold":9792,"date":"2010年9月2日","capital":"160,000,000.00 ","circulate":"83,998,004.00 ","site":"www.xajr.com"},
{"ID":300117,"name":"嘉寓股份","industry":"建筑业","grow":42.2,"hold":51141,"date":"2010年9月2日","capital":"217,200,000.00 ","circulate":"96,702,800.00 ","site":"www.jiayu.com.cn"},
{"ID":300118,"name":"东方日升","industry":"制造业","grow":-15.1,"hold":7661,"date":"2010年9月2日","capital":"560,000,000.00 ","circulate":"280,244,356.00 ","site":"www.china.risenenergy.com"},
{"ID":300119,"name":"瑞普生物","industry":"制造业","grow":28.0,"hold":42881,"date":"2010年9月17日","capital":"193,946,480.00 ","circulate":"76,360,780.00 ","site":"www.ringpu.com"},
{"ID":300120,"name":"经纬电材","industry":"制造业","grow":268.5,"hold":-15986,"date":"2010年9月17日","capital":"169,650,000.00 ","circulate":"59,758,408.00 ","site":"www.jwdc.cn"},
{"ID":300121,"name":"阳谷华泰","industry":"制造业","grow":167.1,"hold":34288,"date":"2010年9月17日","capital":"140,400,000.00 ","circulate":"35,100,000.00 ","site":"www.yghuatai.com"},
{"ID":300122,"name":"智飞生物","industry":"制造业","grow":225.1,"hold":34662,"date":"2010年9月28日","capital":"400,000,000.00 ","circulate":"83,072,500.00 ","site":"www.zhifeishengwu.com"},
{"ID":300123,"name":"太阳鸟","industry":"制造业","grow":22.8,"hold":-30910,"date":"2010年9月28日","capital":"139,105,521.00 ","circulate":"73,405,521.00 ","site":"www.cnsunbird.com"},
{"ID":300124,"name":"汇川技术","industry":"制造业","grow":72.7,"hold":25154,"date":"2010年9月28日","capital":"388,800,000.00 ","circulate":"118,866,690.00 ","site":"www.inovance.cn"},
{"ID":300125,"name":"易世达","industry":"科研服务","grow":-34.6,"hold":46870,"date":"2010年10月13日","capital":"118,000,000.00 ","circulate":"57,484,936.00 ","site":"www.dleast.cc"},
{"ID":300126,"name":"锐奇股份","industry":"制造业","grow":22.9,"hold":-40698,"date":"2010年10月13日","capital":"151,560,000.00 ","circulate":"48,753,936.00 ","site":"www.kenpowertools.com"},
{"ID":300127,"name":"银河磁体","industry":"制造业","grow":-36.6,"hold":28372,"date":"2010年10月13日","capital":"161,573,180.00 ","circulate":"41,000,000.00 ","site":"www.galaxymagnets.com"},
{"ID":300128,"name":"锦富新材","industry":"制造业","grow":40.3,"hold":22402,"date":"2010年10月13日","capital":"204,460,000.00 ","circulate":"94,250,000.00 ","site":"www.jin-fu.cn"},
{"ID":300129,"name":"泰胜风能","industry":"制造业","grow":-34.7,"hold":-28583,"date":"2010年10月19日","capital":"324,000,000.00 ","circulate":"162,079,662.00 ","site":"www.shtsp.com"},
{"ID":300130,"name":"新国都","industry":"制造业","grow":8.7,"hold":-32351,"date":"2010年10月19日","capital":"114,300,000.00 ","circulate":"47,745,000.00 ","site":"www.xinguodu.com"},
{"ID":300131,"name":"英唐智控","industry":"制造业","grow":38.9,"hold":21619,"date":"2010年10月19日","capital":"205,284,991.00 ","circulate":"99,914,653.00 ","site":"www.yitoa.com"},
{"ID":300132,"name":"青松股份","industry":"制造业","grow":-10.3,"hold":23059,"date":"2010年10月26日","capital":"192,960,000.00 ","circulate":"60,198,178.00 ","site":"www.greenpine.cc"},
{"ID":300133,"name":"华策影视","industry":"文化传播","grow":182.3,"hold":-35678,"date":"2010年10月26日","capital":"580,703,100.00 ","circulate":"222,709,466.00 ","site":"www.huacemedia.com"},
{"ID":300134,"name":"大富科技","industry":"制造业","grow":10.2,"hold":28991,"date":"2010年10月26日","capital":"320,000,000.00 ","circulate":"107,480,000.00 ","site":"www.tatfook.com"},
{"ID":300135,"name":"宝利沥青","industry":"制造业","grow":-94.9,"hold":20007,"date":"2010年10月26日","capital":"512,000,000.00 ","circulate":"203,839,701.00 ","site":"www.baolijt.cn"},
{"ID":300136,"name":"信维通信","industry":"制造业","grow":-75.0,"hold":-32602,"date":"2010年11月5日","capital":"133,340,000.00 ","circulate":"83,132,118.00 ","site":"www.sz-sunway.com.cn"},
{"ID":300137,"name":"先河环保","industry":"制造业","grow":-6.0,"hold":37629,"date":"2010年11月5日","capital":"202,800,000.00 ","circulate":"145,137,439.00 ","site":"www.sailhero.com.cn"},
{"ID":300138,"name":"晨光生物","industry":"制造业","grow":42.9,"hold":20562,"date":"2010年11月5日","capital":"179,570,872.00 ","circulate":"53,000,000.00 ","site":"www.cn-cg.com"},
{"ID":300139,"name":"福星晓程","industry":"制造业","grow":27.0,"hold":30711,"date":"2010年11月12日","capital":"109,600,000.00 ","circulate":"41,952,300.00 ","site":"www.xiaocheng.com"},
{"ID":300140,"name":"启源装备","industry":"制造业","grow":-15.5,"hold":16423,"date":"2010年11月12日","capital":"122,000,000.00 ","circulate":"64,832,776.00 ","site":"www.sdricom.com"},
{"ID":300141,"name":"和顺电气","industry":"制造业","grow":33.5,"hold":49846,"date":"2010年11月12日","capital":"165,600,000.00 ","circulate":"84,436,978.00 ","site":"www.cnheshun.com"},
{"ID":300142,"name":"沃森生物","industry":"制造业","grow":37.5,"hold":37064,"date":"2010年11月12日","capital":"182,232,000.00 ","circulate":"64,342,952.00 ","site":"www.walvax.com"},
{"ID":300143,"name":"星河生物","industry":"农林牧渔","grow":-82.5,"hold":40555,"date":"2010年12月9日","capital":"147,400,000.00 ","circulate":"84,292,585.00 ","site":"www.starway.com.cn"},
{"ID":300144,"name":"宋城股份","industry":"公共环保","grow":-34.8,"hold":36261,"date":"2010年12月9日","capital":"558,216,000.00 ","circulate":"173,552,500.00 ","site":"www.chinascgf.com"},
{"ID":300145,"name":"南方泵业","industry":"制造业","grow":28.2,"hold":-22914,"date":"2010年12月9日","capital":"144,000,000.00 ","circulate":"67,764,015.00 ","site":"www.nanfang-pump.com"},
{"ID":300146,"name":"汤臣倍健","industry":"制造业","grow":-2.2,"hold":-36665,"date":"2010年12月15日","capital":"328,080,000.00 ","circulate":"110,882,328.00 ","site":"www.by-health.com.cn"},
{"ID":300147,"name":"香雪制药","industry":"制造业","grow":32.5,"hold":-11925,"date":"2010年12月15日","capital":"392,055,300.00 ","circulate":"239,007,600.00 ","site":"www.xphcn.com"},
{"ID":300148,"name":"天舟文化","industry":"文化传播","grow":-1.8,"hold":-36939,"date":"2010年12月15日","capital":"152,100,000.00 ","circulate":"51,994,928.00 ","site":"www.t-angel.com"},
{"ID":300149,"name":"量子高科","industry":"制造业","grow":-50.2,"hold":1248,"date":"2010年12月22日","capital":"201,000,000.00 ","circulate":"62,648,812.00 ","site":"www.qht.cc"},
{"ID":300150,"name":"世纪瑞尔","industry":"信息技术","grow":15.7,"hold":46797,"date":"2010年12月22日","capital":"270,000,000.00 ","circulate":"149,620,236.00 ","site":"www.c-real.com.cn"},
{"ID":300151,"name":"昌红科技","industry":"制造业","grow":217.2,"hold":14931,"date":"2010年12月22日","capital":"100,500,000.00 ","circulate":"40,094,625.00 ","site":"www.sz-changhong.com"},
{"ID":300152,"name":"燃控科技","industry":"制造业","grow":9.1,"hold":36806,"date":"2010年12月29日","capital":"240,823,000.00 ","circulate":"149,600,000.00 ","site":"www.xcc.com.cn"},
{"ID":300153,"name":"科泰电源","industry":"制造业","grow":-96.6,"hold":4593,"date":"2010年12月29日","capital":"160,000,000.00 ","circulate":"75,715,000.00 ","site":"www.cooltechsh.com"},
{"ID":300154,"name":"瑞凌股份","industry":"制造业","grow":-38.3,"hold":-25537,"date":"2010年12月29日","capital":"223,500,000.00 ","circulate":"78,527,500.00 ","site":"www.riland.com.cn"},
{"ID":300155,"name":"安居宝","industry":"制造业","grow":-51.6,"hold":-32989,"date":"2011年1月7日","capital":"182,658,000.00 ","circulate":"57,756,250.00 ","site":"www.anjubao.com"},
{"ID":300156,"name":"天立环保","industry":"制造业","grow":8.4,"hold":-38522,"date":"2011年1月7日","capital":"288,720,000.00 ","circulate":"151,112,327.00 ","site":"www.tlhb.cn"},
{"ID":300157,"name":"恒泰艾普","industry":"采矿业","grow":242.9,"hold":15529,"date":"2011年1月7日","capital":"369,327,484.00 ","circulate":"210,879,482.00 ","site":"www.ldocean.com.cn"},
{"ID":300158,"name":"振东制药","industry":"制造业","grow":-51.4,"hold":-28067,"date":"2011年1月7日","capital":"288,000,000.00 ","circulate":"89,991,040.00 ","site":"www.zdjt.com"},
{"ID":300159,"name":"新研股份","industry":"制造业","grow":-41.4,"hold":35543,"date":"2011年1月7日","capital":"180,400,000.00 ","circulate":"46,640,000.00 ","site":"www.xjjxy.com.cn"},
{"ID":300160,"name":"秀强股份","industry":"制造业","grow":92.1,"hold":-21427,"date":"2011年1月13日","capital":"186,800,000.00 ","circulate":"67,800,000.00 ","site":"www.jsxq.com"},
{"ID":300161,"name":"华中数控","industry":"制造业","grow":37.9,"hold":-30695,"date":"2011年1月13日","capital":"107,830,000.00 ","circulate":"63,161,538.00 ","site":"www.huazhongcnc.com"},
{"ID":300162,"name":"雷曼光电","industry":"制造业","grow":38.6,"hold":25767,"date":"2011年1月13日","capital":"134,000,000.00 ","circulate":"34,150,000.00 ","site":"www.ledman.cn"},
{"ID":300163,"name":"先锋新材","industry":"制造业","grow":-17.3,"hold":2264,"date":"2011年1月13日","capital":"79,000,000.00 ","circulate":"37,887,188.00 ","site":"www.aplus.cn;www.chinacurtains.com"},
{"ID":300164,"name":"通源石油","industry":"采矿业","grow":39.9,"hold":22288,"date":"2011年1月13日","capital":"237,600,000.00 ","circulate":"143,419,493.00 ","site":"www.tongoiltools.com"},
{"ID":300165,"name":"天瑞仪器","industry":"制造业","grow":34.6,"hold":-17945,"date":"2011年1月25日","capital":"153,920,000.00 ","circulate":"68,085,000.00 ","site":"www.skyray-instrument.com"},
{"ID":300166,"name":"东方国信","industry":"信息技术","grow":44.1,"hold":4457,"date":"2011年1月25日","capital":"123,967,500.00 ","circulate":"41,700,000.00 ","site":"www.bonc.com.cn"},
{"ID":300167,"name":"迪威视讯","industry":"信息技术","grow":-19.0,"hold":-31984,"date":"2011年1月25日","capital":"200,160,000.00 ","circulate":"96,828,750.00 ","site":"www.dvision.cn"},
{"ID":300168,"name":"万达信息","industry":"信息技术","grow":215.2,"hold":-34628,"date":"2011年1月25日","capital":"243,298,760.00 ","circulate":"173,779,810.00 ","site":"www.wondersgroup.com"},
{"ID":300169,"name":"天晟新材","industry":"制造业","grow":48.6,"hold":-29688,"date":"2011年1月25日","capital":"280,500,000.00 ","circulate":"141,837,612.00 ","site":"www.tschina.com"},
{"ID":300170,"name":"汉得信息","industry":"信息技术","grow":4.6,"hold":46293,"date":"2011年2月1日","capital":"266,171,661.00 ","circulate":"148,309,865.00 ","site":"www.hand-china.com"},
{"ID":300171,"name":"东富龙","industry":"制造业","grow":190.0,"hold":37043,"date":"2011年2月1日","capital":"208,000,000.00 ","circulate":"67,600,000.00 ","site":"www.tofflon.com"},
{"ID":300172,"name":"中电环保","industry":"公共环保","grow":149.9,"hold":-34604,"date":"2011年2月1日","capital":"130,000,000.00 ","circulate":"62,449,276.00 ","site":"www.njcec.com"},
{"ID":300173,"name":"松德股份","industry":"制造业","grow":10.3,"hold":-37417,"date":"2011年2月1日","capital":"113,230,000.00 ","circulate":"51,300,795.00 ","site":"www.songde.com.cn"},
{"ID":300174,"name":"元力股份","industry":"制造业","grow":48.0,"hold":30680,"date":"2011年2月1日","capital":"136,000,000.00 ","circulate":"36,297,831.00 ","site":"www.yuanlicarbon.com"},
{"ID":300175,"name":"朗源股份","industry":"制造业","grow":83.6,"hold":21387,"date":"2011年2月15日","capital":"470,800,000.00 ","circulate":"264,915,200.00 ","site":"www.lontrue.com"},
{"ID":300176,"name":"鸿特精密","industry":"制造业","grow":40.4,"hold":611,"date":"2011年2月15日","capital":"107,280,000.00 ","circulate":"35,484,360.00 ","site":"www.hongteo.com.cn"},
{"ID":300177,"name":"中海达","industry":"制造业","grow":16.6,"hold":27640,"date":"2011年2月15日","capital":"201,948,800.00 ","circulate":"90,068,892.00 ","site":"www.zhdgps.com"},
{"ID":300178,"name":"腾邦国际","industry":"商务服务","grow":6.8,"hold":-4473,"date":"2011年2月15日","capital":"122,300,000.00 ","circulate":"71,400,000.00 ","site":"www.tempus.cn"},
{"ID":300179,"name":"四方达","industry":"制造业","grow":7.3,"hold":-17385,"date":"2011年2月15日","capital":"216,000,000.00 ","circulate":"86,663,918.00 ","site":"www.sf-diamond.com.cn"},
{"ID":300180,"name":"华峰超纤","industry":"制造业","grow":40.5,"hold":15744,"date":"2011年2月22日","capital":"158,000,000.00 ","circulate":"75,412,500.00 ","site":"0.00 "},
{"ID":300181,"name":"佐力药业","industry":"制造业","grow":50.2,"hold":40266,"date":"2011年2月22日","capital":"144,000,000.00 ","circulate":"89,587,575.00 ","site":"www.zuoli.com"},
{"ID":300182,"name":"捷成股份","industry":"信息技术","grow":121.9,"hold":2076,"date":"2011年2月22日","capital":"222,331,850.00 ","circulate":"54,600,000.00 ","site":"www.jetsen.com.cn"},
{"ID":300183,"name":"东软载波","industry":"信息技术","grow":88.4,"hold":14156,"date":"2011年2月22日","capital":"220,000,000.00 ","circulate":"55,000,000.00 ","site":"www.eastsoft.com.cn"},
{"ID":300184,"name":"力源信息","industry":"批发零售","grow":29.3,"hold":-39409,"date":"2011年2月22日","capital":"100,050,000.00 ","circulate":"66,177,713.00 ","site":"www.icbase.com"},
{"ID":300185,"name":"通裕重工","industry":"制造业","grow":-66.4,"hold":10968,"date":"2011年3月8日","capital":"900,000,000.00 ","circulate":"485,867,804.00 ","site":"www.tongyuheavy.com"},
{"ID":300186,"name":"大华农","industry":"制造业","grow":-90.2,"hold":-4567,"date":"2011年3月8日","capital":"534,000,000.00 ","circulate":"134,000,000.00 ","site":"www.gddhn.com"},
{"ID":300187,"name":"永清环保","industry":"公共环保","grow":46.1,"hold":-24900,"date":"2011年3月8日","capital":"200,340,000.00 ","circulate":"55,650,000.00 ","site":"www.yonker.com.cn"},
{"ID":300188,"name":"美亚柏科","industry":"信息技术","grow":12.1,"hold":-17521,"date":"2011年3月16日","capital":"221,813,200.00 ","circulate":"54,000,000.00 ","site":"www.xm-my.com.cn; www.300188.cn"},
{"ID":300189,"name":"神农大丰","industry":"农林牧渔","grow":-66.3,"hold":48883,"date":"2011年3月16日","capital":"256,000,000.00 ","circulate":"111,040,000.00 ","site":"www.sndf.com.cn"},
{"ID":300190,"name":"维尔利","industry":"公共环保","grow":-99.0,"hold":-15532,"date":"2011年3月16日","capital":"156,456,000.00 ","circulate":"63,515,520.00 ","site":"www.jswelle.com.cn"},
{"ID":300191,"name":"潜能恒信","industry":"采矿业","grow":-9.1,"hold":-33677,"date":"2011年3月16日","capital":"320,000,000.00 ","circulate":"91,760,000.00 ","site":"www.sinogeo.com"},
{"ID":300192,"name":"科斯伍德","industry":"制造业","grow":-1.9,"hold":-20559,"date":"2011年3月22日","capital":"110,250,000.00 ","circulate":"54,000,000.00 ","site":"www.szkinks.com"},
{"ID":300193,"name":"佳士科技","industry":"制造业","grow":24.1,"hold":-25476,"date":"2011年3月22日","capital":"221,500,000.00 ","circulate":"115,362,231.00 ","site":"www.jasic.com.cn"},
{"ID":300194,"name":"福安药业","industry":"制造业","grow":19.8,"hold":-11946,"date":"2011年3月22日","capital":"173,420,000.00 ","circulate":"47,975,879.00 ","site":"www.fapharm.com"},
{"ID":300195,"name":"长荣股份","industry":"制造业","grow":43.3,"hold":10892,"date":"2011年3月29日","capital":"142,224,000.00 ","circulate":"35,887,250.00 ","site":"www.mkmchina.com"},
{"ID":300196,"name":"长海股份","industry":"制造业","grow":168.7,"hold":32938,"date":"2011年3月29日","capital":"120,000,000.00 ","circulate":"50,793,750.00 ","site":"www.changhaigfrp.com"},
{"ID":300197,"name":"铁汉生态","industry":"建筑业","grow":43.9,"hold":42029,"date":"2011年3月29日","capital":"315,805,878.00 ","circulate":"82,453,355.00 ","site":"www.sztechand.com"},
{"ID":300198,"name":"纳川股份","industry":"制造业","grow":-30.2,"hold":-33930,"date":"2011年4月7日","capital":"209,038,410.00 ","circulate":"96,150,962.00 ","site":"www.superpipe.cn"},
{"ID":300199,"name":"翰宇药业","industry":"制造业","grow":33.3,"hold":14688,"date":"2011年4月7日","capital":"400,000,000.00 ","circulate":"184,865,125.00 ","site":"www.hybio.com.cn"},
{"ID":300200,"name":"高盟新材","industry":"制造业","grow":212.3,"hold":6268,"date":"2011年4月7日","capital":"213,600,000.00 ","circulate":"80,284,456.00 ","site":"www.co-mens.com"},
{"ID":300201,"name":"海伦哲","industry":"制造业","grow":253.7,"hold":25529,"date":"2011年4月7日","capital":"352,000,000.00 ","circulate":"225,327,508.00 ","site":"www.xzhlz.com"},
{"ID":300202,"name":"聚龙股份","industry":"制造业","grow":15.3,"hold":-21296,"date":"2011年4月15日","capital":"305,280,000.00 ","circulate":"103,680,000.00 ","site":"www.julong.cc"},
{"ID":300203,"name":"聚光科技","industry":"制造业","grow":24.8,"hold":31740,"date":"2011年4月15日","capital":"445,000,000.00 ","circulate":"88,858,299.00 ","site":"www.fpi-inc.com"},
{"ID":300204,"name":"舒泰神","industry":"制造业","grow":14.9,"hold":27117,"date":"2011年4月15日","capital":"240,120,000.00 ","circulate":"66,741,793.00 ","site":"www.staidson.com"},
{"ID":300205,"name":"天喻信息","industry":"制造业","grow":4.9,"hold":11663,"date":"2011年4月21日","capital":"215,028,000.00 ","circulate":"86,359,365.00 ","site":"www.whty.com.cn"},
{"ID":300206,"name":"理邦仪器","industry":"制造业","grow":21.3,"hold":40765,"date":"2011年4月21日","capital":"130,000,000.00 ","circulate":"54,841,843.00 ","site":"www.edan.com.cn"},
{"ID":300207,"name":"欣旺达","industry":"制造业","grow":13.3,"hold":-10251,"date":"2011年4月21日","capital":"244,400,000.00 ","circulate":"75,739,853.00 ","site":"www.sunwoda.com"},
{"ID":300208,"name":"恒顺电气","industry":"制造业","grow":43.9,"hold":18047,"date":"2011年4月26日","capital":"284,920,000.00 ","circulate":"188,555,750.00 ","site":"www.qdhengshun.com"},
{"ID":300209,"name":"天泽信息","industry":"信息技术","grow":33.7,"hold":-32653,"date":"2011年4月26日","capital":"160,000,000.00 ","circulate":"40,000,000.00 ","site":"www.itrackstar.com"},
{"ID":300210,"name":"森远股份","industry":"制造业","grow":-58.1,"hold":-2922,"date":"2011年4月26日","capital":"134,730,000.00 ","circulate":"35,455,905.00 ","site":"www.assyrb.com"},
{"ID":300211,"name":"亿通科技","industry":"制造业","grow":202.3,"hold":11517,"date":"2011年5月5日","capital":"64,495,200.00 ","circulate":"22,980,681.00 ","site":"www.yitong-group.com"},
{"ID":300212,"name":"易华录","industry":"信息技术","grow":2.5,"hold":-3264,"date":"2011年5月5日","capital":"268,000,000.00 ","circulate":"139,757,100.00 ","site":"www.ehualu.com"},
{"ID":300213,"name":"佳讯飞鸿","industry":"制造业","grow":-42.7,"hold":-6463,"date":"2011年5月5日","capital":"126,000,000.00 ","circulate":"38,089,235.00 ","site":"www.jiaxun.com"},
{"ID":300214,"name":"日科化学","industry":"制造业","grow":-2.3,"hold":-33509,"date":"2011年5月11日","capital":"202,500,000.00 ","circulate":"79,599,771.00 ","site":"www.rikechem.com"},
{"ID":300215,"name":"电科院","industry":"科研服务","grow":240.1,"hold":43099,"date":"2011年5月11日","capital":"360,000,000.00 ","circulate":"199,999,250.00 ","site":"www.eeti-easa.com"},
{"ID":300216,"name":"千山药机","industry":"制造业","grow":38.9,"hold":36830,"date":"2011年5月11日","capital":"183,674,400.00 ","circulate":"87,100,000.00 ","site":"www.chinasun.com.cn"},
{"ID":300217,"name":"东方电热","industry":"制造业","grow":8.1,"hold":-31250,"date":"2011年5月18日","capital":"197,736,000.00 ","circulate":"77,715,663.00 ","site":"www.dongfang-heater.com"},
{"ID":300218,"name":"安利股份","industry":"制造业","grow":174.0,"hold":-19229,"date":"2011年5月18日","capital":"211,200,000.00 ","circulate":"59,136,000.00 ","site":"www.chinapuleather.com"},
{"ID":300219,"name":"鸿利光电","industry":"制造业","grow":80.8,"hold":36394,"date":"2011年5月18日","capital":"245,466,000.00 ","circulate":"107,757,345.00 ","site":"www.honglitronic.com"},
{"ID":300220,"name":"金运激光","industry":"制造业","grow":41.3,"hold":-28177,"date":"2011年5月25日","capital":"70,000,000.00 ","circulate":"21,657,850.00 ","site":"www.goldenlaser.cn"},
{"ID":300221,"name":"银禧科技","industry":"制造业","grow":-44.2,"hold":-29928,"date":"2011年5月25日","capital":"200,000,000.00 ","circulate":"102,500,000.00 ","site":"www.silverage.cn"},
{"ID":300222,"name":"科大智能","industry":"制造业","grow":21.9,"hold":38639,"date":"2011年5月25日","capital":"108,000,000.00 ","circulate":"35,846,622.00 ","site":"www.csg.com.cn"},
{"ID":300223,"name":"北京君正","industry":"制造业","grow":21.4,"hold":27486,"date":"2011年5月31日","capital":"104,000,000.00 ","circulate":"46,264,652.00 ","site":"www.ingenic.cn"},
{"ID":300224,"name":"正海磁材","industry":"制造业","grow":64.1,"hold":47221,"date":"2011年5月31日","capital":"240,000,000.00 ","circulate":"74,722,500.00 ","site":"www.zhmag.com"},
{"ID":300225,"name":"金力泰","industry":"制造业","grow":22.0,"hold":-36744,"date":"2011年5月31日","capital":"130,650,000.00 ","circulate":"52,376,077.00 ","site":"www.knt.cn"},
{"ID":300226,"name":"上海钢联","industry":"信息技术","grow":21.2,"hold":20058,"date":"2011年6月8日","capital":"120,000,000.00 ","circulate":"43,618,125.00 ","site":"www.mysteel.com"},
{"ID":300227,"name":"光韵达","industry":"制造业","grow":48.5,"hold":-24923,"date":"2011年6月8日","capital":"134,000,000.00 ","circulate":"68,500,000.00 ","site":"www.sunshine-laser.com"},
{"ID":300228,"name":"富瑞特装","industry":"制造业","grow":257.3,"hold":-28766,"date":"2011年6月8日","capital":"134,000,000.00 ","circulate":"79,628,433.00 ","site":"www.furuise.com"},
{"ID":300229,"name":"拓尔思","industry":"信息技术","grow":262.2,"hold":24575,"date":"2011年6月15日","capital":"204,743,650.00 ","circulate":"69,230,020.00 ","site":"www.trs.com.cn"},
{"ID":300230,"name":"永利带业","industry":"制造业","grow":-26.9,"hold":27526,"date":"2011年6月15日","capital":"161,524,800.00 ","circulate":"56,916,000.00 ","site":"www.yonglibelt.com"},
{"ID":300231,"name":"银信科技","industry":"信息技术","grow":-0.3,"hold":-28670,"date":"2011年6月15日","capital":"120,000,000.00 ","circulate":"40,800,000.00 ","site":"www.trustfar.cn"},
{"ID":300232,"name":"洲明科技","industry":"制造业","grow":10.3,"hold":-6886,"date":"2011年6月22日","capital":"101,036,075.00 ","circulate":"40,068,200.00 ","site":"www.unilumin.com"},
{"ID":300233,"name":"金城医药","industry":"制造业","grow":129.6,"hold":20324,"date":"2011年6月22日","capital":"121,000,000.00 ","circulate":"59,453,500.00 ","site":"www.jinchengpharm.com"},
{"ID":300234,"name":"开尔新材","industry":"制造业","grow":12.1,"hold":33275,"date":"2011年6月22日","capital":"120,000,000.00 ","circulate":"30,000,000.00 ","site":"www.zjke.com"},
{"ID":300235,"name":"方直科技","industry":"信息技术","grow":220.4,"hold":9304,"date":"2011年6月29日","capital":"88,000,000.00 ","circulate":"30,064,050.00 ","site":"www.kingsunsoft.com"},
{"ID":300236,"name":"上海新阳","industry":"制造业","grow":171.1,"hold":2662,"date":"2011年6月29日","capital":"85,180,000.00 ","circulate":"21,500,000.00 ","site":"www.sinyang.com.cn"},
{"ID":300237,"name":"美晨科技","industry":"制造业","grow":-33.4,"hold":-502,"date":"2011年6月29日","capital":"57,000,000.00 ","circulate":"16,500,000.00 ","site":"www.meichen.cc"},
{"ID":300238,"name":"冠昊生物","industry":"制造业","grow":-96.7,"hold":-41973,"date":"2011年7月6日","capital":"122,200,000.00 ","circulate":"72,336,033.00 ","site":"www.grandhopebio.com"},
{"ID":300239,"name":"东宝生物","industry":"制造业","grow":19.0,"hold":-11055,"date":"2011年7月6日","capital":"197,548,000.00 ","circulate":"118,612,975.00 ","site":"www.dongbaoshengwu.com"},
{"ID":300240,"name":"飞力达","industry":"运输仓储","grow":16.0,"hold":36097,"date":"2011年7月6日","capital":"167,520,000.00 ","circulate":"76,865,250.00 ","site":"www.feiliks.com"},
{"ID":300241,"name":"瑞丰光电","industry":"制造业","grow":113.9,"hold":39394,"date":"2011年7月12日","capital":"216,229,993.00 ","circulate":"80,569,920.00 ","site":"www.refond.com"},
{"ID":300242,"name":"明家科技","industry":"制造业","grow":47.7,"hold":16022,"date":"2011年7月12日","capital":"75,000,000.00 ","circulate":"26,852,500.00 ","site":"www.migsurge.com"},
{"ID":300243,"name":"瑞丰高材","industry":"制造业","grow":171.2,"hold":19209,"date":"2011年7月12日","capital":"102,720,000.00 ","circulate":"51,055,104.00 ","site":"www.ruifengchemical.com"},
{"ID":300244,"name":"迪安诊断","industry":"卫生","grow":-41.0,"hold":8617,"date":"2011年7月19日","capital":"119,574,000.00 ","circulate":"60,413,184.00 ","site":"www.dazd.cn"},
{"ID":300245,"name":"天玑科技","industry":"信息技术","grow":34.6,"hold":-39155,"date":"2011年7月19日","capital":"134,000,000.00 ","circulate":"53,348,255.00 ","site":"www.dnt.com.cn"},
{"ID":300246,"name":"宝莱特","industry":"制造业","grow":33.5,"hold":-37345,"date":"2011年7月19日","capital":"146,088,000.00 ","circulate":"53,772,480.00 ","site":"www.blt.com.cn"},
{"ID":300247,"name":"桑乐金","industry":"制造业","grow":-25.6,"hold":40035,"date":"2011年7月29日","capital":"122,625,000.00 ","circulate":"52,824,375.00 ","site":"www.saunaking.com.cn"},
{"ID":300248,"name":"新开普","industry":"信息技术","grow":24.4,"hold":10568,"date":"2011年7月29日","capital":"89,200,000.00 ","circulate":"34,145,000.00 ","site":"www.newcapec.com.cn"},
{"ID":300249,"name":"依米康","industry":"制造业","grow":148.7,"hold":6356,"date":"2011年8月3日","capital":"156,800,000.00 ","circulate":"76,550,200.00 ","site":"www.sunrisegroup.com.cn"},
{"ID":300250,"name":"初灵信息","industry":"制造业","grow":61.0,"hold":-35678,"date":"2011年8月3日","capital":"80,000,000.00 ","circulate":"27,848,000.00 ","site":"www.cncr-it.com"},
{"ID":300251,"name":"光线传媒","industry":"文化传播","grow":15.6,"hold":46491,"date":"2011年8月3日","capital":"506,352,000.00 ","circulate":"138,150,705.00 ","site":"www.ewang.com"},
{"ID":300252,"name":"金信诺","industry":"制造业","grow":250.4,"hold":-15737,"date":"2011年8月18日","capital":"164,344,996.00 ","circulate":"57,440,806.00 ","site":"www.kingsignal.com"},
{"ID":300253,"name":"卫宁软件","industry":"信息技术","grow":-1.2,"hold":10060,"date":"2011年8月18日","capital":"107,000,000.00 ","circulate":"56,188,257.00 ","site":"www.winning.com.cn"},
{"ID":300254,"name":"仟源制药","industry":"制造业","grow":45.7,"hold":13062,"date":"2011年8月19日","capital":"133,800,000.00 ","circulate":"33,800,000.00 ","site":"www.cy-pharm.com"},
{"ID":300255,"name":"常山药业","industry":"制造业","grow":11.1,"hold":-12402,"date":"2011年8月19日","capital":"188,418,700.00 ","circulate":"103,023,823.00 ","site":"www.heparin.cn"},
{"ID":300256,"name":"星星科技","industry":"制造业","grow":11.9,"hold":45421,"date":"2011年8月19日","capital":"150,000,000.00 ","circulate":"82,868,250.00 ","site":"www.first-panel.com"},
{"ID":300257,"name":"开山股份","industry":"制造业","grow":-11.5,"hold":-24216,"date":"2011年8月19日","capital":"429,000,000.00 ","circulate":"146,188,706.00 ","site":"www.kaishancomp.com.cn"},
{"ID":300258,"name":"精锻科技","industry":"制造业","grow":-20.7,"hold":24145,"date":"2011年8月26日","capital":"180,000,000.00 ","circulate":"70,863,750.00 ","site":"www.ppforging.com"},
{"ID":300259,"name":"新天科技","industry":"制造业","grow":46.5,"hold":47938,"date":"2011年8月31日","capital":"181,632,000.00 ","circulate":"66,880,212.00 ","site":"www.suntront.com"},
{"ID":300260,"name":"新莱应材","industry":"制造业","grow":203.8,"hold":-22444,"date":"2011年9月6日","capital":"100,050,000.00 ","circulate":"29,675,625.00 ","site":"www.kinglai.com.cn"},
{"ID":300261,"name":"雅本化学","industry":"制造业","grow":39.7,"hold":34461,"date":"2011年9月6日","capital":"232,192,000.00 ","circulate":"62,464,000.00 ","site":"www.abachem.com"},
{"ID":300262,"name":"巴安水务","industry":"建筑业","grow":-51.1,"hold":-23197,"date":"2011年9月16日","capital":"266,800,000.00 ","circulate":"120,857,532.00 ","site":"www.safbon.com"},
{"ID":300263,"name":"隆华节能","industry":"制造业","grow":276.7,"hold":23718,"date":"2011年9月16日","capital":"163,320,000.00 ","circulate":"56,085,000.00 ","site":"www.longhuachuanre.com"},
{"ID":300264,"name":"佳创视讯","industry":"信息技术","grow":-63.5,"hold":-255,"date":"2011年9月16日","capital":"153,000,000.00 ","circulate":"93,303,825.00 ","site":"www.avit.com.cn"},
{"ID":300265,"name":"通光线缆","industry":"制造业","grow":277.5,"hold":-27825,"date":"2011年9月16日","capital":"135,000,000.00 ","circulate":"35,000,000.00 ","site":"www.tgjt.cn"},
{"ID":300266,"name":"兴源过滤","industry":"制造业","grow":29.0,"hold":-36788,"date":"2011年9月27日","capital":"116,480,000.00 ","circulate":"29,120,000.00 ","site":"www.xingyuan.com"},
{"ID":300267,"name":"尔康制药","industry":"制造业","grow":24.0,"hold":-15338,"date":"2011年9月27日","capital":"239,200,000.00 ","circulate":"75,972,126.00 ","site":"www.hnerkang.com"},
{"ID":300268,"name":"万福生科","industry":"制造业","grow":-88.4,"hold":-14126,"date":"2011年9月27日","capital":"134,000,000.00 ","circulate":"34,000,000.00 ","site":"www.wanfushk.com"},
{"ID":300269,"name":"联建光电","industry":"制造业","grow":34.9,"hold":-6560,"date":"2011年10月12日","capital":"117,728,000.00 ","circulate":"52,800,835.00 ","site":"www.lcjh.com"},
{"ID":300270,"name":"中威电子","industry":"制造业","grow":23.2,"hold":51420,"date":"2011年10月12日","capital":"120,000,000.00 ","circulate":"44,599,876.00 ","site":"www.obtelecom.com"},
{"ID":300271,"name":"华宇软件","industry":"信息技术","grow":25.0,"hold":-20404,"date":"2011年10月26日","capital":"148,000,000.00 ","circulate":"92,187,726.00 ","site":"www.thunisoft.com"},
{"ID":300272,"name":"开能环保","industry":"制造业","grow":40.1,"hold":-5044,"date":"2011年11月2日","capital":"188,888,700.00 ","circulate":"87,668,264.00 ","site":"www.canature.com"},
{"ID":300273,"name":"和佳股份","industry":"制造业","grow":9.3,"hold":-30204,"date":"2011年10月26日","capital":"440,055,000.00 ","circulate":"225,936,150.00 ","site":"www.hokai.com"},
{"ID":300274,"name":"阳光电源","industry":"制造业","grow":25.3,"hold":-2070,"date":"2011年11月2日","capital":"322,560,000.00 ","circulate":"141,120,000.00 ","site":"www.sungrowpower.com"},
{"ID":300275,"name":"梅安森","industry":"信息技术","grow":28.5,"hold":45131,"date":"2011年11月2日","capital":"164,276,000.00 ","circulate":"57,176,000.00 ","site":"www.cqmas.com"},
{"ID":300276,"name":"三丰智能","industry":"制造业","grow":-70.5,"hold":-18125,"date":"2011年11月15日","capital":"124,800,000.00 ","circulate":"45,583,546.00 ","site":"www.sfgs.com.cn"},
{"ID":300277,"name":"海联讯","industry":"信息技术","grow":134.1,"hold":19002,"date":"2011年11月23日","capital":"134,000,000.00 ","circulate":"37,166,220.00 ","site":"www.hirisun.com"},
{"ID":300278,"name":"华昌达","industry":"制造业","grow":206.0,"hold":33469,"date":"2011年12月16日","capital":"173,400,000.00 ","circulate":"43,400,000.00 ","site":"www.hchd.com.cn"},
{"ID":300279,"name":"和晶科技","industry":"制造业","grow":49.0,"hold":-9961,"date":"2011年12月29日","capital":"120,000,000.00 ","circulate":"54,860,503.00 ","site":"www.hodgen-china.com"},
{"ID":300280,"name":"南通锻压","industry":"制造业","grow":82.8,"hold":-39574,"date":"2011年12月29日","capital":"128,000,000.00 ","circulate":"32,000,000.00 ","site":"www.ntdy.com.cn"},
{"ID":300281,"name":"金明精机","industry":"制造业","grow":44.9,"hold":2427,"date":"2011年12月29日","capital":"120,000,000.00 ","circulate":"48,450,000.00 ","site":"www.jmjj.com"},
{"ID":300282,"name":"汇冠股份","industry":"制造业","grow":-66.1,"hold":42787,"date":"2011年12月29日","capital":"71,806,800.00 ","circulate":"23,205,000.00 ","site":"www.irtouch.com"},
{"ID":300283,"name":"温州宏丰","industry":"制造业","grow":-44.4,"hold":17856,"date":"2012年1月10日","capital":"92,080,300.00 ","circulate":"23,790,000.00 ","site":"www.wzhf.com"},
{"ID":300284,"name":"苏交科","industry":"科研服务","grow":157.9,"hold":-39224,"date":"2012年1月10日","capital":"240,000,000.00 ","circulate":"131,061,051.00 ","site":"www.jsti.com;www.jstri.com"},
{"ID":300285,"name":"国瓷材料","industry":"制造业","grow":-58.6,"hold":13545,"date":"2012年1月13日","capital":"62,400,000.00 ","circulate":"15,600,000.00 ","site":"www.sinocera.com.cn"},
{"ID":300286,"name":"安科瑞","industry":"制造业","grow":190.2,"hold":-28938,"date":"2012年1月13日","capital":"71,330,000.00 ","circulate":"17,340,000.00 ","site":"www.acrel.cn"},
{"ID":300287,"name":"飞利信","industry":"信息技术","grow":285.8,"hold":36355,"date":"2012年2月1日","capital":"126,000,000.00 ","circulate":"57,678,750.00 ","site":"www.philisense.com"},
{"ID":300288,"name":"朗玛信息","industry":"信息技术","grow":26.0,"hold":18097,"date":"2012年2月16日","capital":"106,800,000.00 ","circulate":"26,800,000.00 ","site":"www.longmaster.com.cn"},
{"ID":300289,"name":"利德曼","industry":"制造业","grow":-18.9,"hold":49107,"date":"2012年2月16日","capital":"153,600,000.00 ","circulate":"46,656,000.00 ","site":"www.leadmanbio.com"},
{"ID":300290,"name":"荣科科技","industry":"信息技术","grow":25.8,"hold":20732,"date":"2012年2月16日","capital":"136,000,000.00 ","circulate":"50,044,574.00 ","site":"www.bringspring.com"},
{"ID":300291,"name":"华录百纳","industry":"文化传播","grow":-44.7,"hold":-1557,"date":"2012年2月9日","capital":"132,000,000.00 ","circulate":"72,600,000.00 ","site":"www.hlbn-ent.com"},
{"ID":300292,"name":"吴通通讯","industry":"制造业","grow":8.3,"hold":39984,"date":"2012年2月29日","capital":"100,050,000.00 ","circulate":"31,050,000.00 ","site":"www.jswutong.com"},
{"ID":300293,"name":"蓝英装备","industry":"制造业","grow":241.0,"hold":33293,"date":"2012年3月8日","capital":"180,000,000.00 ","circulate":"45,000,000.00 ","site":"www.chnsbs.net"},
{"ID":300294,"name":"博雅生物","industry":"制造业","grow":-70.8,"hold":35512,"date":"2012年3月8日","capital":"75,800,000.00 ","circulate":"31,884,468.00 ","site":"www.china-boya.com"},
{"ID":300295,"name":"三六五网","industry":"信息技术","grow":24.5,"hold":-38515,"date":"2012年3月15日","capital":"53,350,000.00 ","circulate":"24,658,582.00 ","site":"www.house365.com"},
{"ID":300296,"name":"利亚德","industry":"制造业","grow":43.6,"hold":34705,"date":"2012年3月15日","capital":"150,000,000.00 ","circulate":"37,500,000.00 ","site":"www.leyard.com"},
{"ID":300297,"name":"蓝盾股份","industry":"信息技术","grow":-67.8,"hold":36929,"date":"2012年3月15日","capital":"196,000,000.00 ","circulate":"111,108,100.00 ","site":"www.bluedon.com"},
{"ID":300298,"name":"三诺生物","industry":"制造业","grow":51.1,"hold":-38592,"date":"2012年3月19日","capital":"132,000,000.00 ","circulate":"33,000,000.00 ","site":"www.sinocare.com.cn"},
{"ID":300299,"name":"富春通信","industry":"信息技术","grow":-44.2,"hold":29278,"date":"2012年3月19日","capital":"120,600,000.00 ","circulate":"47,832,250.00 ","site":"www.forcom.com.cn"},
{"ID":300300,"name":"汉鼎股份","industry":"信息技术","grow":22.9,"hold":-10315,"date":"2012年3月19日","capital":"191,400,000.00 ","circulate":"59,785,000.00 ","site":"www.hakim.com.cn"},
{"ID":300301,"name":"长方照明","industry":"制造业","grow":1.8,"hold":-22536,"date":"2012年3月21日","capital":"270,000,000.00 ","circulate":"68,766,896.00 ","site":"www.cfled.com"},
{"ID":300302,"name":"同有科技","industry":"信息技术","grow":72.4,"hold":19748,"date":"2012年3月21日","capital":"60,000,000.00 ","circulate":"15,000,000.00 ","site":"www.toyou.com.cn"},
{"ID":300303,"name":"聚飞光电","industry":"制造业","grow":0.5,"hold":8583,"date":"2012年3月19日","capital":"217,600,000.00 ","circulate":"109,019,872.00 ","site":"www.jfled.com.cn"},
{"ID":300304,"name":"云意电气","industry":"制造业","grow":39.3,"hold":49066,"date":"2012年3月21日","capital":"100,000,000.00 ","circulate":"25,000,000.00 ","site":"www.yunyi-china.com"},
{"ID":300305,"name":"裕兴股份","industry":"制造业","grow":-9.4,"hold":-27430,"date":"2012年3月29日","capital":"144,000,000.00 ","circulate":"36,000,000.00 ","site":"www.czyuxing.com"},
{"ID":300306,"name":"远方光电","industry":"制造业","grow":214.6,"hold":39966,"date":"2012年3月29日","capital":"120,000,000.00 ","circulate":"37,079,580.00 ","site":"www.everfine.cn"},
{"ID":300307,"name":"慈星股份","industry":"制造业","grow":-41.1,"hold":-40885,"date":"2012年3月29日","capital":"802,000,000.00 ","circulate":"156,708,330.00 ","site":"www.ci-xing.com"},
{"ID":300308,"name":"中际装备","industry":"制造业","grow":10.1,"hold":2563,"date":"2012年4月10日","capital":"120,006,000.00 ","circulate":"41,860,125.00 ","site":"www.zhongji.cc"},
{"ID":300309,"name":"吉艾科技","industry":"制造业","grow":51.1,"hold":4892,"date":"2012年4月10日","capital":"217,274,000.00 ","circulate":"57,180,876.00 ","site":"www.gi-tech.cn"},
{"ID":300310,"name":"宜通世纪","industry":"信息技术","grow":13.5,"hold":40786,"date":"2012年4月25日","capital":"176,000,000.00 ","circulate":"44,000,000.00 ","site":"www.etonetech.com"},
{"ID":300311,"name":"任子行","industry":"信息技术","grow":-14.0,"hold":30164,"date":"2012年4月25日","capital":"70,700,000.00 ","circulate":"20,700,000.00 ","site":"www.1218.com.cn"},
{"ID":300312,"name":"邦讯技术","industry":"信息技术","grow":51.4,"hold":13623,"date":"2012年5月8日","capital":"160,020,000.00 ","circulate":"62,820,000.00 ","site":"www.boomsense.com"},
{"ID":300313,"name":"天山生物","industry":"农林牧渔","grow":24.6,"hold":6795,"date":"2012年4月25日","capital":"90,910,000.00 ","circulate":"35,254,250.00 ","site":"www.tsbulls.net"},
{"ID":300314,"name":"戴维医疗","industry":"制造业","grow":1.5,"hold":-5468,"date":"2012年5月8日","capital":"160,000,000.00 ","circulate":"43,000,000.00 ","site":"www.nbdavid.com"},
{"ID":300315,"name":"掌趣科技","industry":"信息技术","grow":201.4,"hold":-37762,"date":"2012年5月11日","capital":"360,052,000.00 ","circulate":"178,822,985.00 ","site":"www.ourpalm.com"},
{"ID":300316,"name":"晶盛机电","industry":"制造业","grow":41.6,"hold":-4779,"date":"2012年5月11日","capital":"266,700,000.00 ","circulate":"86,370,150.00 ","site":"www.jsjd.cc"},
{"ID":300317,"name":"珈伟股份","industry":"制造业","grow":136.1,"hold":32706,"date":"2012年5月11日","capital":"140,000,000.00 ","circulate":"53,246,638.00 ","site":"www.jiawei.com"},
{"ID":300318,"name":"博晖创新","industry":"制造业","grow":213.8,"hold":-25358,"date":"2012年5月23日","capital":"163,840,000.00 ","circulate":"60,155,184.00 ","site":"www.bohui-tech.com"},
{"ID":300319,"name":"麦捷科技","industry":"制造业","grow":21.6,"hold":48405,"date":"2012年5月23日","capital":"53,340,000.00 ","circulate":"18,276,000.00 ","site":"www.szmicrogate.com"},
{"ID":300320,"name":"海达股份","industry":"制造业","grow":-98.5,"hold":-7460,"date":"2012年6月1日","capital":"133,340,000.00 ","circulate":"59,570,362.00 ","site":"www.haida.cn"},
{"ID":300321,"name":"同大股份","industry":"制造业","grow":-41.4,"hold":9472,"date":"2012年5月23日","capital":"44,400,000.00 ","circulate":"18,023,078.00 ","site":"www.tongdahdcx.com"},
{"ID":300322,"name":"硕贝德","industry":"制造业","grow":-64.2,"hold":-16367,"date":"2012年6月8日","capital":"112,014,000.00 ","circulate":"53,500,944.00 ","site":"www.speed-hz.com"},
{"ID":300323,"name":"华灿光电","industry":"制造业","grow":288.7,"hold":-29015,"date":"2012年6月1日","capital":"300,000,000.00 ","circulate":"129,832,500.00 ","site":"www.hcsemitek.com"},
{"ID":300324,"name":"旋极信息","industry":"信息技术","grow":29.9,"hold":-9625,"date":"2012年6月8日","capital":"112,000,000.00 ","circulate":"32,805,000.00 ","site":"www.watertek.com"},
{"ID":300325,"name":"德威新材","industry":"制造业","grow":8.6,"hold":-2481,"date":"2012年6月1日","capital":"160,000,000.00 ","circulate":"94,396,780.00 ","site":"www.chinadewei.com"},
{"ID":300326,"name":"凯利泰","industry":"制造业","grow":42.6,"hold":-32030,"date":"2012年6月13日","capital":"76,875,000.00 ","circulate":"25,125,000.00 ","site":"www.kineticmedinc.com.cn"},
{"ID":300327,"name":"中颖电子","industry":"制造业","grow":-83.8,"hold":-34788,"date":"2012年6月13日","capital":"140,800,000.00 ","circulate":"97,183,048.00 ","site":"www.sinowealth.com"},
{"ID":300328,"name":"宜安科技","industry":"制造业","grow":36.8,"hold":-18933,"date":"2012年6月19日","capital":"112,000,000.00 ","circulate":"28,000,000.00 ","site":"www.e-ande.com"},
{"ID":300329,"name":"海伦钢琴","industry":"制造业","grow":21.9,"hold":-7818,"date":"2012年6月19日","capital":"133,980,000.00 ","circulate":"68,588,538.00 ","site":"www.hailunpiano.com"},
{"ID":300330,"name":"华虹计通","industry":"信息技术","grow":269.6,"hold":-18602,"date":"2012年6月19日","capital":"80,000,000.00 ","circulate":"52,402,158.00 ","site":"www.huahongjt.com"},
{"ID":300331,"name":"苏大维格","industry":"制造业","grow":6.2,"hold":-29223,"date":"2012年6月28日","capital":"62,000,000.00 ","circulate":"36,750,987.00 ","site":"www.svgoptronics.com"},
{"ID":300332,"name":"天壕节能","industry":"科研服务","grow":6.9,"hold":7188,"date":"2012年6月28日","capital":"320,000,000.00 ","circulate":"226,667,500.00 ","site":"www.trce.com.cn"},
{"ID":300333,"name":"兆日科技","industry":"信息技术","grow":-93.3,"hold":-32581,"date":"2012年6月28日","capital":"112,000,000.00 ","circulate":"67,314,352.00 ","site":"www.sinosun.com.cn"},
{"ID":300334,"name":"津膜科技","industry":"制造业","grow":68.8,"hold":33707,"date":"2012年7月5日","capital":"174,000,000.00 ","circulate":"68,542,499.00 ","site":"www.motimo.com"},
{"ID":300335,"name":"迪森股份","industry":"水电煤气","grow":29.5,"hold":16241,"date":"2012年7月10日","capital":"209,233,251.00 ","circulate":"101,099,539.00 ","site":"www.devotiongroup.com"},
{"ID":300336,"name":"新文化","industry":"文化传播","grow":-86.1,"hold":-31066,"date":"2012年7月10日","capital":"96,000,000.00 ","circulate":"35,887,500.00 ","site":"www.ncmedia.com.cn"},
{"ID":300337,"name":"银邦股份","industry":"制造业","grow":-62.4,"hold":-8794,"date":"2012年7月18日","capital":"186,800,000.00 ","circulate":"46,800,000.00 ","site":"www.cn-yinbang.com"},
{"ID":300338,"name":"开元仪器","industry":"制造业","grow":7.8,"hold":-19138,"date":"2012年7月26日","capital":"90,000,000.00 ","circulate":"22,500,000.00 ","site":"www.chs5e.com"},
{"ID":300339,"name":"润和软件","industry":"信息技术","grow":29.9,"hold":-18221,"date":"2012年7月18日","capital":"153,480,000.00 ","circulate":"38,380,000.00 ","site":"www.hoperun.com"},
{"ID":300340,"name":"科恒股份","industry":"制造业","grow":3.7,"hold":35431,"date":"2012年7月26日","capital":"100,000,000.00 ","circulate":"25,000,000.00 ","site":"www.keheng.com.cn"},
{"ID":300341,"name":"麦迪电气","industry":"制造业","grow":33.7,"hold":37699,"date":"2012年7月26日","capital":"92,000,000.00 ","circulate":"23,000,000.00 ","site":"www.motic-electric.com"},
{"ID":300342,"name":"天银机电","industry":"制造业","grow":41.1,"hold":-22666,"date":"2012年7月26日","capital":"100,000,000.00 ","circulate":"25,000,000.00 ","site":"www.tyjd.cc"},
{"ID":300343,"name":"联创节能","industry":"制造业","grow":47.3,"hold":38935,"date":"2012年8月1日","capital":"40,000,000.00 ","circulate":"10,000,000.00 ","site":"www.lecron.cn"},
{"ID":300344,"name":"太空板业","industry":"制造业","grow":44.2,"hold":-13977,"date":"2012年8月1日","capital":"160,832,000.00 ","circulate":"40,208,000.00 ","site":"www.taikong.cn"},
{"ID":300345,"name":"红宇新材","industry":"制造业","grow":-79.2,"hold":4841,"date":"2012年8月1日","capital":"96,000,000.00 ","circulate":"24,000,000.00 ","site":"www.zghyu.com"},
{"ID":300346,"name":"南大光电","industry":"制造业","grow":169.5,"hold":21404,"date":"2012年8月7日","capital":"100,540,000.00 ","circulate":"25,140,000.00 ","site":"www.natachem.com"},
{"ID":300347,"name":"泰格医药","industry":"科研服务","grow":-4.7,"hold":-10964,"date":"2012年8月17日","capital":"106,800,000.00 ","circulate":"26,798,000.00 ","site":"www.tigermed.net"},
{"ID":300348,"name":"长亮科技","industry":"信息技术","grow":-95.2,"hold":18225,"date":"2012年8月17日","capital":"51,700,000.00 ","circulate":"13,000,000.00 ","site":"www.sunline.cn"},
{"ID":300349,"name":"金卡股份","industry":"制造业","grow":-80.6,"hold":15762,"date":"2012年8月17日","capital":"90,000,000.00 ","circulate":"22,500,000.00 ","site":"www.china-goldcard.com"},
{"ID":300350,"name":"华鹏飞","industry":"运输仓储","grow":5.7,"hold":-20741,"date":"2012年8月21日","capital":"86,670,000.00 ","circulate":"21,670,000.00 ","site":"www.huapengfei.com"},
{"ID":300351,"name":"永贵电器","industry":"制造业","grow":131.1,"hold":39626,"date":"2012年9月20日","capital":"102,180,000.00 ","circulate":"26,000,000.00 ","site":"www.yonggui.com"},
{"ID":300352,"name":"北信源","industry":"信息技术","grow":-54.1,"hold":3443,"date":"2012年9月12日","capital":"133,400,000.00 ","circulate":"33,400,000.00 ","site":"www.vrv.com.cn"},
{"ID":300353,"name":"东土科技","industry":"制造业","grow":38.9,"hold":39181,"date":"2012年9月27日","capital":"85,620,480.00 ","circulate":"21,440,000.00 ","site":"www.kyland.com.cn"},
{"ID":300354,"name":"东华测试","industry":"制造业","grow":10.0,"hold":-29464,"date":"2012年9月20日","capital":"66,524,136.00 ","circulate":"16,635,000.00 ","site":"www.dhtest.com"},
{"ID":300355,"name":"蒙草抗旱","industry":"建筑业","grow":37.7,"hold":-11031,"date":"2012年9月27日","capital":"205,465,500.00 ","circulate":"51,540,000.00 ","site":"www.nmhxy.com"},
{"ID":300356,"name":"光一科技","industry":"制造业","grow":108.0,"hold":41028,"date":"2012年10月9日","capital":"130,005,000.00 ","circulate":"32,505,000.00 ","site":"www.elefirst.com"}]